MANIFEST.in
README
setup.py
Flask_Social.egg-info/PKG-INFO
Flask_Social.egg-info/SOURCES.txt
Flask_Social.egg-info/dependency_links.txt
Flask_Social.egg-info/not-zip-safe
Flask_Social.egg-info/requires.txt
Flask_Social.egg-info/top_level.txt
flask_social/__init__.py
flask_social/datastore/__init__.py
flask_social/datastore/mongoengine.py
flask_social/datastore/sqlalchemy.py
tests/functional_tests.py