Metadata-Version: 1.0
Name: Flask-Social
Version: 1.0.0
Summary: Simple OAuth provider integration for Flask-Security
Home-page: https://github.com/mattupstate/flask-social
Author: Matthew Wright
Author-email: matt@nobien.net
License: MIT
Platform: any
Classifier: Development Status :: 4 - Beta
Classifier: Environment :: Web Environment
Classifier: Intended Audience :: Developers
Classifier: License :: OSI Approved :: MIT License
Classifier: Operating System :: OS Independent
Classifier: Programming Language :: Python
Classifier: Topic :: Internet :: WWW/HTTP :: Dynamic Content
Classifier: Topic :: Software Development :: Libraries :: Python Modules
